main.py
WeatherMeow-0.1.dist-info/LICENSE
WeatherMeow-0.1.dist-info/METADATA
WeatherMeow-0.1.dist-info/WHEEL
WeatherMeow-0.1.dist-info/entry_points.txt
WeatherMeow-0.1.dist-info/top_level.txt
WeatherMeow-0.1.dist-info/RECORD
